Metadata-Version: 2.1
Name: chalice-restful
Version: 1.0.0
Summary: Provides a more structured way of writing RESTful APIs with Chalice.
Home-page: https://github.com/JoshuaLight/chalice-restful
Author: Joshua Light
Author-email: j.light.developer@gmail.com
License: MIT
Platform: UNKNOWN
Classifier: Development Status :: 5 - Production/Stable
Classifier: Intended Audience :: Developers
Classifier: Topic :: Software Development :: Libraries :: Python Modules
Classifier: License :: OSI Approved :: MIT License
Classifier: Programming Language :: Python :: 3.7
